[{"name":"Norman Milligan","description":"Character in Fabricante_de_lágrimas","url":"https://es.wikipedia.org/wiki/Fabricante_de_lágrimas","lang":"en","source_count":1},{"name":"Margaret Stoker","description":"Character in Fabricante_de_lágrimas","url":"https://es.wikipedia.org/wiki/Fabricante_de_lágrimas","lang":"en","source_count":1},{"name":"Anna Milligan","description":"Character in Fabricante_de_lágrimas","url":"https://es.wikipedia.org/wiki/Fabricante_de_lágrimas","lang":"en","source_count":1},{"name":"Peter Corrin","description":"Character in Fabricante_de_lágrimas","url":"https://es.wikipedia.org/wiki/Fabricante_de_lágrimas","lang":"en","source_count":1},{"name":"Rigel Wilde","description":"Character in Fabricante_de_lágrimas","url":"https://es.wikipedia.org/wiki/Fabricante_de_lágrimas","lang":"en","source_count":1},{"name":"Nica Diver","description":"Character in Fabricante_de_lágrimas","url":"https://es.wikipedia.org/wiki/Fabricante_de_lágrimas","lang":"en","source_count":1},{"name":"Adeline","description":"Character in Fabricante_de_lágrimas","url":"https://es.wikipedia.org/wiki/Fabricante_de_lágrimas","lang":"en","source_count":1},{"name":"Billie","description":"Character in Fabricante_de_lágrimas","url":"https://es.wikipedia.org/wiki/Fabricante_de_lágrimas","lang":"en","source_count":1},{"name":"Lionel","description":"Character in Fabricante_de_lágrimas","url":"https://es.wikipedia.org/wiki/Fabricante_de_lágrimas","lang":"en","source_count":1},{"name":"Phelps","description":"Character in Fabricante_de_lágrimas","url":"https://es.wikipedia.org/wiki/Fabricante_de_lágrimas","lang":"en","source_count":1},{"name":"Dalma","description":"Character in Fabricante_de_lágrimas","url":"https://es.wikipedia.org/wiki/Fabricante_de_lágrimas","lang":"en","source_count":1},{"name":"Miki","description":"Character in Fabricante_de_lágrimas","url":"https://es.wikipedia.org/wiki/Fabricante_de_lágrimas","lang":"en","source_count":1},{"name":"Asia","description":"Character in Fabricante_de_lágrimas","url":"https://es.wikipedia.org/wiki/Fabricante_de_lágrimas","lang":"en","source_count":1}]